<annotation>
	<folder>images</folder>
	<filename>20200203_160355_037.jpg</filename>
	<path>/home/zema/Documents/Appolodorus/TrainingAndTestingImages/TrainingImages/PreparedTrainingImages/train/images/20200203_160355_037.jpg</path>
	<source>
		<database>Unknown</database>
	</source>
	<size>
		<width>360</width>
		<height>240</height>
		<depth>3</depth>
	</size>
	<segmented>0</segmented>
	<object>
		<name>Washer</name>
		<pose>Unspecified</pose>
		<truncated>0</truncated>
		<difficult>0</difficult>
		<bndbox>
			<xmin>147</xmin>
			<ymin>27</ymin>
			<xmax>166</xmax>
			<ymax>40</ymax>
		</bndbox>
	</object>
	<object>
		<name>Washer</name>
		<pose>Unspecified</pose>
		<truncated>0</truncated>
		<difficult>0</difficult>
		<bndbox>
			<xmin>192</xmin>
			<ymin>35</ymin>
			<xmax>210</xmax>
			<ymax>47</ymax>
		</bndbox>
	</object>
	<object>
		<name>Washer</name>
		<pose>Unspecified</pose>
		<truncated>0</truncated>
		<difficult>0</difficult>
		<bndbox>
			<xmin>253</xmin>
			<ymin>33</ymin>
			<xmax>271</xmax>
			<ymax>44</ymax>
		</bndbox>
	</object>
	<object>
		<name>Nut</name>
		<pose>Unspecified</pose>
		<truncated>0</truncated>
		<difficult>0</difficult>
		<bndbox>
			<xmin>238</xmin>
			<ymin>63</ymin>
			<xmax>259</xmax>
			<ymax>83</ymax>
		</bndbox>
	</object>
	<object>
		<name>Nut</name>
		<pose>Unspecified</pose>
		<truncated>0</truncated>
		<difficult>0</difficult>
		<bndbox>
			<xmin>286</xmin>
			<ymin>66</ymin>
			<xmax>311</xmax>
			<ymax>92</ymax>
		</bndbox>
	</object>
	<object>
		<name>Nut</name>
		<pose>Unspecified</pose>
		<truncated>0</truncated>
		<difficult>0</difficult>
		<bndbox>
			<xmin>321</xmin>
			<ymin>101</ymin>
			<xmax>347</xmax>
			<ymax>129</ymax>
		</bndbox>
	</object>
	<object>
		<name>Bolt</name>
		<pose>Unspecified</pose>
		<truncated>0</truncated>
		<difficult>0</difficult>
		<bndbox>
			<xmin>250</xmin>
			<ymin>108</ymin>
			<xmax>296</xmax>
			<ymax>191</ymax>
		</bndbox>
	</object>
	<object>
		<name>FinishedAssembly</name>
		<pose>Unspecified</pose>
		<truncated>0</truncated>
		<difficult>0</difficult>
		<bndbox>
			<xmin>157</xmin>
			<ymin>65</ymin>
			<xmax>227</xmax>
			<ymax>114</ymax>
		</bndbox>
	</object>
	<object>
		<name>FinishedAssembly</name>
		<pose>Unspecified</pose>
		<truncated>0</truncated>
		<difficult>0</difficult>
		<bndbox>
			<xmin>93</xmin>
			<ymin>42</ymin>
			<xmax>155</xmax>
			<ymax>81</ymax>
		</bndbox>
	</object>
	<object>
		<name>FalseAssembly</name>
		<pose>Unspecified</pose>
		<truncated>0</truncated>
		<difficult>0</difficult>
		<bndbox>
			<xmin>35</xmin>
			<ymin>99</ymin>
			<xmax>123</xmax>
			<ymax>174</ymax>
		</bndbox>
	</object>
	<object>
		<name>FalseAssembly</name>
		<pose>Unspecified</pose>
		<truncated>0</truncated>
		<difficult>0</difficult>
		<bndbox>
			<xmin>145</xmin>
			<ymin>118</ymin>
			<xmax>193</xmax>
			<ymax>212</ymax>
		</bndbox>
	</object>
</annotation>
